{"id":"1035","name":"Vigorous Pink Rose Bush","transitionsToward":[{"actorID":"210","targetID":"1034","newActorID":"209","newTargetID":"1035"},{"actorID":"382","targetID":"1034","newActorID":"235","newTargetID":"1035"}],"transitionsAway":[],"transitionsTimed":[{"targetID":"1035","newTargetID":"1033","decay":"2m"}],"version":101,"depth":24,"difficulty":"0.56","techTree":[{"id":"210","nodes":[{"id":"209","nodes":[{"id":"192","nodes":[]},{"id":"184","nodes":[]}]},{"id":"141","nodes":null}]},{"id":"1034","nodes":[{"decay":"2m"},{"id":"1019","nodes":[{"decay":"2m"},{"id":"1018","nodes":[]}]}]}],"recipe":{"steps":[[{"id":"1015","targetID":"1013","hand":true}],[{"id":"1016","actorID":"135","targetID":"1015"}],[{"id":"1022","actorID":"1016","targetID":"1021"},{"id":"336","actorID":"292","targetID":"211"}],[{"id":"1023","targetID":"1022","decay":"30s"},{"id":"1101","actorID":"336"}],[{"id":"1024","targetID":"1023","hand":true},{"id":"213","actorID":"139","targetID":"1101"}],[{"id":"382","actorID":"235","targetID":"510"},{"id":"1017","actorID":"1024","targetID":"213"}],[{"id":"1018","actorID":"382","targetID":"1017"}],[{"id":"210","actorID":"209","targetID":"141"},{"id":"1034","targetID":"1019","decay":"4m"}],[{"id":"1035","actorID":"210","targetID":"1034"}]],"ingredients":["209","1021","235","510","292","139","135","1013","211","141"]}}