{"id":"132","name":"Yew Branch","transitionsToward":[{"targetID":"153","newActorID":"132","newTargetID":"406","hand":true}],"transitionsAway":[{"actorID":"34","targetID":"132","newActorID":"34","newTargetID":"131","tool":true},{"actorID":"71","targetID":"132","newActorID":"71","newTargetID":"72","tool":true},{"actorID":"334","targetID":"132","newActorID":"334","newTargetID":"72","tool":true}],"version":20,"complexity":1,"difficulty":0.040783034257748776,"techTree":[{"id":"153","nodes":null}],"recipe":{"steps":[[{"id":"132","targetID":"153","hand":true}]],"ingredients":["153"]}}