{"id":"200","name":"Rabbit Fur Loincloth","transitionsToward":[{"actorID":"192","targetID":"183","newActorID":"191","newTargetID":"200"}],"transitionsAway":[],"transitionsTimed":[{"targetID":"200","newTargetID":"866","decay":"5h"}],"version":20,"depth":21,"difficulty":"0.42","clothing":"b","insulation":0.17,"size":1,"techTree":[{"id":"192","nodes":[{"id":"191","nodes":[{"id":"135","nodes":[]},{"id":"189","nodes":[]}]},{"id":"58","nodes":[{"id":"57","nodes":[]},{"id":"57","nodes":[]}]}]},{"id":"183","nodes":[{"id":"182","nodes":[{"id":"135","nodes":[]},{"id":"180","nodes":[]}]}]}],"recipe":{"steps":[[{"id":"162","actorID":"160","targetID":"164"}],[{"id":"176","targetID":"174","decay":"25s"}],[{"id":"57","count":2,"targetID":"50","hand":true},{"id":"180","targetID":"176","hand":true}],[{"id":"58","actorID":"57","targetID":"57"},{"id":"182","actorID":"135","targetID":"180"}],[{"id":"192","actorID":"191","targetID":"58"},{"id":"183","targetID":"182","hand":true}],[{"id":"200","actorID":"192","targetID":"183"}]],"ingredients":["191","160","135","164","50","50"]}}