{"id":"220","name":"Milkweed Seed","transitionsToward":[{"targetID":"55","newActorID":"220","newTargetID":"55","targetRemains":true,"hand":true}],"transitionsAway":[{"actorID":"220","targetID":"213","newTargetID":"214"},{"actorID":"220","targetID":"82","newTargetID":"82","targetRemains":true},{"actorID":"220","targetID":"83","newTargetID":"83","targetRemains":true},{"actorID":"220","targetID":"346","newTargetID":"346","targetRemains":true}],"transitionsTimed":[],"version":20,"depth":4,"difficulty":"0.04","size":1,"techTree":[{"id":"55","nodes":[{"id":"52","nodes":[{"decay":"20s"},{"id":"51","nodes":[]}]}]}],"recipe":{"steps":[[{"id":"220","targetID":"55","hand":true}]],"ingredients":["55"]}}