{"id":"270","name":"Raw Rabbit Pie","transitionsToward":[{"actorID":"255","targetID":"264","newActorID":"235","newTargetID":"270"}],"transitionsAway":[{"actorID":"270","targetID":"250","newActorID":"274","newTargetID":"250","targetRemains":true}],"transitionsTimed":[],"version":20,"depth":19,"difficulty":3,"size":1,"techTree":[{"id":"255","nodes":[{"id":"34","nodes":[{"id":"33","nodes":null},{"id":"32","nodes":null}]},{"id":"254","nodes":[{"id":"181","nodes":[]},{"id":"235","nodes":[]}]}]},{"id":"264","nodes":[{"id":"252","nodes":[{"id":"382","nodes":[]},{"id":"251","nodes":[]}]},{"id":"236","nodes":[{"id":"241","nodes":[]}]}]}],"recipe":{"steps":[[{"id":"162","actorID":"160","targetID":"164"}],[{"id":"176","targetID":"174","decay":"25s"}],[{"id":"180","targetID":"176","hand":true}],[{"id":"182","actorID":"135","targetID":"180"}],[{"id":"181","targetID":"182","hand":true}],[{"id":"254","actorID":"181","targetID":"235"}],[{"id":"255","actorID":"34","targetID":"254"},{"id":"264","subSteps":[[{"id":"126","targetID":"125","hand":true}],[{"id":"233","actorID":"33","targetID":"126"}],[{"id":"234","actorID":"33","targetID":"233"}],[{"id":"240","actorID":"239","targetID":"234"}],[{"id":"241","actorID":"240","targetID":"282"}],[{"id":"236","actorID":"241"}],[{"id":"264","actorID":"252","targetID":"236"}]]}],[{"id":"270","actorID":"255","targetID":"264"}]],"ingredients":["252","235","282","160","239","135","164","34","125","33"]}}