{"id":"282","name":"Firing Adobe Kiln","foodValue":"0","heatValue":"0","clothing":"n","numUses":"1","complexity":84,"techTree":[{"id":"248","nodes":[{"id":"67","nodes":[{"id":"34","nodes":[]},{"id":"64","nodes":[]}]},{"id":"82","nodes":[{"id":"72","nodes":[]},{"id":"80","nodes":[]}]}]},{"id":"281","nodes":[{"id":"72","nodes":[{"id":"71","nodes":[]},{"id":"64","nodes":[]}]},{"id":"238","nodes":[{"id":"127","nodes":[]},{"id":"237","nodes":[]}]}]}],"transitionsToward":[{"actorID":"248","targetID":"281","newActorID":"248","newTargetID":"282","targetNumUses":"1","targetRemains":false,"hand":false,"tool":true},{"actorID":"67","targetID":"282","newActorID":"248","newTargetID":"282","targetNumUses":"1","targetRemains":true,"hand":false,"tool":false},{"actorID":"248","targetID":"299","newActorID":"248","newTargetID":"282","targetNumUses":"1","targetRemains":false,"hand":false,"tool":true},{"actorID":"284","targetID":"282","newActorID":"283","newTargetID":"282","targetNumUses":"1","targetRemains":true,"hand":false,"tool":false},{"actorID":"240","targetID":"282","newActorID":"241","newTargetID":"282","targetNumUses":"1","targetRemains":true,"hand":false,"tool":false},{"actorID":"295","targetID":"282","newActorID":"296","newTargetID":"282","targetNumUses":"1","targetRemains":true,"hand":false,"tool":false}],"transitionsAway":[{"targetID":"282","newTargetID":"238","targetNumUses":"1","targetRemains":false,"hand":false,"tool":false,"decay":"30s"},{"actorID":"67","targetID":"282","newActorID":"248","newTargetID":"282","targetNumUses":"1","targetRemains":true,"hand":false,"tool":false},{"actorID":"127","targetID":"282","newTargetID":"293","targetNumUses":"1","targetRemains":false,"hand":false,"tool":false},{"actorID":"284","targetID":"282","newActorID":"283","newTargetID":"282","targetNumUses":"1","targetRemains":true,"hand":false,"tool":false},{"actorID":"240","targetID":"282","newActorID":"241","newTargetID":"282","targetNumUses":"1","targetRemains":true,"hand":false,"tool":false},{"actorID":"295","targetID":"282","newActorID":"296","newTargetID":"282","targetNumUses":"1","targetRemains":true,"hand":false,"tool":false}]}