{"id":"292","name":"Basket","containable":"1","containSize":"2,vertSlotRot","permanent":"0,minPickupAge","heldInHand":"0","blocksWalking":"0,leftBlockingRadius","mapChance":"0.000000","biomes":["grassland"],"heatValue":"0","rValue":"0.000000","person":"0,noSpawn","male":"0","deathMarker":"0","floor":"0","floorHugging":"0","foodValue":"0","speedMult":"1.000000","heldOffset":"18.000000,19.000000","clothing":"n","clothingOffset":"-27.000000,72.000000","deadlyDistance":"0","useDistance":"1","sounds":"74:0.250000,49:0.250000,-1:0.250000,-1:1.000000","creationSoundInitialOnly":"1","numSlots":"3#timeStretch","slotSize":"1","slotPos":"5.000000,-18.000000,vert","numSprites":"2","headIndex":"-1","bodyIndex":"-1","backFootIndex":"-1","frontFootIndex":"-1","numUses":"1","useVanishIndex":"-1","useAppearIndex":"-1","pixHeight":"0","hasSprite":true,"transitionsToward":[{"actor":{"id":"124","name":"Reed Bundle"},"target":{"id":"124","name":"Reed Bundle"},"newTarget":{"id":"292","name":"Basket"},"targetRemains":false,"hand":false,"tool":false},{"actor":{"id":"227","name":"Straw"},"target":{"id":"227","name":"Straw"},"newTarget":{"id":"292","name":"Basket"},"targetRemains":false,"hand":false,"tool":false},{"actor":{"id":"298","name":"Basket of Charcoal"},"newActor":{"id":"292","name":"Basket"},"newTarget":{"id":"300","name":"Big Charcoal Pile - 3"},"targetRemains":false,"hand":false,"tool":false},{"actor":{"id":"298","name":"Basket of Charcoal"},"target":{"id":"303","name":"Forge"},"newActor":{"id":"292","name":"Basket"},"newTarget":{"id":"305","name":"Forge with Charcoal"},"targetRemains":false,"hand":false,"tool":false},{"actor":{"id":"336","name":"Basket of Soil"},"newActor":{"id":"292","name":"Basket"},"newTarget":{"id":"213","name":"Tilled Row"},"targetRemains":false,"hand":false,"tool":false},{"actor":{"id":"336","name":"Basket of Soil"},"target":{"id":"410","name":"Empty Fertile Soil Pit"},"newActor":{"id":"292","name":"Basket"},"newTarget":{"id":"411","name":"Fertile Soil Pit - partial"},"targetRemains":false,"hand":false,"tool":false},{"actor":{"id":"336","name":"Basket of Soil"},"target":{"id":"411","name":"Fertile Soil Pit - partial"},"newActor":{"id":"292","name":"Basket"},"newTarget":{"id":"411","name":"Fertile Soil Pit - partial"},"targetRemains":true,"hand":false,"tool":false},{"actor":{"id":"336","name":"Basket of Soil"},"target":{"id":"411","name":"Fertile Soil Pit - partial"},"newActor":{"id":"292","name":"Basket"},"newTarget":{"id":"211","name":"Fertile Soil Deposit"},"targetRemains":false,"hand":false,"tool":false},{"actor":{"id":"356","name":"Basket of Bones"},"newActor":{"id":"292","name":"Basket"},"newTarget":{"id":"357","name":"Bone Pile"},"targetRemains":false,"hand":false,"tool":false},{"actor":{"id":"571","name":"Basket of Mouflon Bones"},"newActor":{"id":"292","name":"Basket"},"newTarget":{"id":"572","name":"Mouflon Bones - dumped"},"targetRemains":false,"hand":false,"tool":false},{"actor":{"id":"590","name":"Basket of Sheep Bones"},"newActor":{"id":"292","name":"Basket"},"newTarget":{"id":"589","name":"Sheep Bones - dumped"},"targetRemains":false,"hand":false,"tool":false}],"transitionsAway":[{"actor":{"id":"292","name":"Basket"},"target":{"id":"211","name":"Fertile Soil Deposit"},"newActor":{"id":"336","name":"Basket of Soil"},"newTarget":{"id":"411","name":"Fertile Soil Pit - partial"},"targetRemains":false,"hand":false,"tool":false},{"actor":{"id":"292","name":"Basket"},"target":{"id":"213","name":"Tilled Row"},"newActor":{"id":"336","name":"Basket of Soil"},"targetRemains":false,"hand":false,"tool":false},{"actor":{"id":"292","name":"Basket"},"target":{"id":"299","name":"Adobe Kiln with Charcoal"},"newActor":{"id":"298","name":"Basket of Charcoal"},"newTarget":{"id":"238","name":"Adobe Kiln"},"targetRemains":false,"hand":false,"tool":false},{"actor":{"id":"292","name":"Basket"},"target":{"id":"300","name":"Big Charcoal Pile - 3"},"newActor":{"id":"298","name":"Basket of Charcoal"},"targetRemains":false,"hand":false,"tool":false},{"actor":{"id":"292","name":"Basket"},"target":{"id":"305","name":"Forge with Charcoal"},"newActor":{"id":"298","name":"Basket of Charcoal"},"newTarget":{"id":"303","name":"Forge"},"targetRemains":false,"hand":false,"tool":false},{"actor":{"id":"292","name":"Basket"},"target":{"id":"357","name":"Bone Pile"},"newActor":{"id":"356","name":"Basket of Bones"},"targetRemains":false,"hand":false,"tool":false},{"actor":{"id":"292","name":"Basket"},"target":{"id":"411","name":"Fertile Soil Pit - partial"},"newActor":{"id":"336","name":"Basket of Soil"},"newTarget":{"id":"411","name":"Fertile Soil Pit - partial"},"targetRemains":true,"hand":false,"tool":false},{"actor":{"id":"292","name":"Basket"},"target":{"id":"411","name":"Fertile Soil Pit - partial"},"newActor":{"id":"336","name":"Basket of Soil"},"newTarget":{"id":"410","name":"Empty Fertile Soil Pit"},"targetRemains":false,"hand":false,"tool":false},{"actor":{"id":"292","name":"Basket"},"target":{"id":"566","name":"Mouflon Bones"},"newActor":{"id":"571","name":"Basket of Mouflon Bones"},"targetRemains":false,"hand":false,"tool":false},{"actor":{"id":"292","name":"Basket"},"target":{"id":"572","name":"Mouflon Bones - dumped"},"newActor":{"id":"571","name":"Basket of Mouflon Bones"},"targetRemains":false,"hand":false,"tool":false},{"actor":{"id":"292","name":"Basket"},"target":{"id":"588","name":"Sheep Bones"},"newActor":{"id":"590","name":"Basket of Sheep Bones"},"targetRemains":false,"hand":false,"tool":false},{"actor":{"id":"292","name":"Basket"},"target":{"id":"615","name":"Eaten Carrot Row"},"newActor":{"id":"336","name":"Basket of Soil"},"targetRemains":false,"hand":false,"tool":false},{"actor":{"id":"292","name":"Basket"},"target":{"id":"624","name":"Composted Soil"},"newActor":{"id":"336","name":"Basket of Soil"},"newTarget":{"id":"624","name":"Composted Soil"},"targetRemains":true,"hand":false,"tool":false},{"actor":{"id":"292","name":"Basket"},"target":{"id":"624","name":"Composted Soil"},"newActor":{"id":"336","name":"Basket of Soil"},"targetRemains":false,"hand":false,"tool":false},{"actor":{"id":"292","name":"Basket"},"target":{"id":"87","name":"Fresh Grave"},"newActor":{"id":"356","name":"Basket of Bones"},"targetRemains":false,"hand":false,"tool":false},{"actor":{"id":"292","name":"Basket"},"target":{"id":"88","name":"Grave"},"newActor":{"id":"356","name":"Basket of Bones"},"targetRemains":false,"hand":false,"tool":false},{"actor":{"id":"292","name":"Basket"},"target":{"id":"89","name":"Old Grave"},"newActor":{"id":"356","name":"Basket of Bones"},"targetRemains":false,"hand":false,"tool":false}]}