{"id":"338","name":"Stump","transitionsToward":[{"targetID":"343","newActorID":"344","newTargetID":"338","hand":true},{"targetID":"339","newActorID":"345","newTargetID":"338","hand":true}],"transitionsAway":[{"targetID":"338","decay":"60m"},{"actorID":"502","newActorUses":"-1","targetID":"338","newActorID":"502","newTargetID":"496","tool":true},{"actorID":"502","actorUses":"last","targetID":"338","newActorID":"858","newTargetID":"496"}],"version":20,"complexity":283,"difficulty":0.6775147928994083,"techTree":[{"id":"343","nodes":[{"id":"342","nodes":[{"id":"334","nodes":[]},{"id":"49","nodes":null}]}]}],"recipe":{"steps":[[{"id":"342","actorID":"334","targetID":"49"}],[{"id":"343","targetID":"342","hand":true}],[{"id":"338","targetID":"343","hand":true}]],"ingredients":["334","49"]}}