{"id":"457","name":"Steel File Blank","foodValue":"0","heatValue":"0","clothing":"n","numUses":"1","complexity":395,"techTree":[{"id":"450","nodes":[{"decay":"10s"},{"id":"447","nodes":[{"id":"441","nodes":[]},{"id":"446","nodes":[]}]}]}],"transitionsToward":[{"targetID":"450","newActorID":"457","newTargetID":"291","targetNumUses":"1","targetRemains":false,"hand":true,"tool":false}],"transitionsAway":[{"actorID":"457","targetID":"235","newTargetID":"495","targetNumUses":"1","targetRemains":false,"hand":false,"tool":false},{"actorID":"518","targetID":"457","newActorID":"518","newTargetID":"464","targetNumUses":"1","targetRemains":false,"hand":false,"tool":true}]}