{"id":"495","name":"Crucible with Scrap Steel","version":49,"foodValue":"0","heatValue":"0","clothing":"n","numUses":"1","complexity":402,"techTree":[{"id":"333","nodes":[{"id":"332","nodes":[{"decay":"10s"},{"id":"331","nodes":[]}]}]},{"id":"235","nodes":[{"id":"283","nodes":[{"id":"284","nodes":[]},{"id":"282","nodes":[]}]}]}],"transitionsToward":[{"actorID":"333","targetID":"235","newTargetID":"495","targetNumUses":"1","targetRemains":false,"hand":false,"tool":false},{"actorID":"455","targetID":"235","newTargetID":"495","targetNumUses":"1","targetRemains":false,"hand":false,"tool":false},{"actorID":"454","targetID":"235","newTargetID":"495","targetNumUses":"1","targetRemains":false,"hand":false,"tool":false},{"actorID":"456","targetID":"235","newTargetID":"495","targetNumUses":"1","targetRemains":false,"hand":false,"tool":false},{"actorID":"457","targetID":"235","newTargetID":"495","targetNumUses":"1","targetRemains":false,"hand":false,"tool":false},{"actorID":"459","targetID":"235","newTargetID":"495","targetNumUses":"1","targetRemains":false,"hand":false,"tool":false},{"actorID":"501","targetID":"235","newTargetID":"495","targetNumUses":"1","targetRemains":false,"hand":false,"tool":false},{"actorID":"685","targetID":"235","newTargetID":"495","targetNumUses":"1","targetRemains":false,"hand":false,"tool":false},{"actorID":"458","targetID":"235","newTargetID":"495","targetNumUses":"1","targetRemains":false,"hand":false,"tool":false},{"actorID":"559","targetID":"235","newTargetID":"495","targetNumUses":"1","targetRemains":false,"hand":false,"tool":false},{"actorID":"460","targetID":"235","newTargetID":"495","targetNumUses":"1","targetRemains":false,"hand":false,"tool":false}],"transitionsAway":[{"actorID":"236","targetID":"495","newTargetID":"319","targetNumUses":"1","targetRemains":false,"hand":false,"tool":false}]}