{"id":"545","name":"Domestic Lamb - just left parent","foodValue":"0","heatValue":"0","clothing":"n","numUses":"1","complexity":158,"techTree":[{"id":"544","nodes":[{"decay":"6s"},{"id":"541","nodes":[{"decay":"3s"},{"id":"601","nodes":[]}]}]}],"transitionsToward":[{"actorID":"544","newActorID":"545","newTargetID":"541","targetRemains":false,"hand":false,"tool":false},{"actorID":"600","newActorID":"545","newTargetID":"575","targetRemains":false,"hand":false,"tool":false}],"transitionsAway":[{"targetID":"545","newTargetID":"542","targetNumUses":"1","targetRemains":false,"hand":false,"tool":false,"decay":"1s"}]}