{"id":"582","name":"Huge Ball of Yarn","transitionsToward":[{"actorID":"581","targetID":"580","newTargetID":"582"}],"transitionsAway":[{"actorID":"583","targetID":"582","newActorID":"583","newTargetID":"585","tool":true}],"transitionsTimed":[],"version":52,"depth":66,"difficulty":8,"size":1,"techTree":[{"id":"581","nodes":[{"id":"1125","nodes":[{"id":"579","nodes":[]},{"id":"578","nodes":[]}]},{"id":"1125","nodes":[{"id":"579","nodes":[]},{"id":"578","nodes":[]}]}]},{"id":"580","nodes":[{"id":"581","nodes":[{"id":"1125","nodes":[]},{"id":"1125","nodes":[]}]},{"id":"581","nodes":[{"id":"1125","nodes":[]},{"id":"1125","nodes":[]}]}]}],"recipe":{"steps":[[{"id":"39","count":6,"actorID":"34","targetID":"36"}],[{"id":"40","count":6,"targetID":"39","hand":true},{"id":"253","count":6,"actorID":"31","targetID":"235"}],[{"id":"258","count":6,"actorID":"40","targetID":"253"},{"id":"542","count":6,"subSteps":[[{"id":"545","count":6,"actorID":"544"}],[{"id":"542","count":6,"targetID":"545","decay":"1s"}]]}],[{"id":"602","count":6,"actorID":"258","targetID":"542"}],[{"id":"575","count":6,"targetID":"602","decay":"45s"}],[{"id":"577","count":6,"actorID":"568","targetID":"575"}],[{"id":"578","count":6,"targetID":"577","hand":true}],[{"id":"1125","count":6,"actorID":"579","targetID":"578"}],[{"id":"581","count":3,"actorID":"1125","targetID":"1125"}],[{"id":"580","actorID":"581","targetID":"581"}],[{"id":"582","actorID":"581","targetID":"580"}]],"ingredients":["579","568","544","235","34","31","31","31","31","31","31","36","36","36","36","36","36"]}}