{"id":"605","name":"Dead Mouflon Lamb","transitionsToward":[{"targetID":"603","newTargetID":"605","targetNumUses":"10","decay":"3s"}],"transitionsAway":[{"targetID":"605","decay":"5m"},{"actorID":"605","targetID":"620","newTargetID":"620","targetNumUses":"10","targetRemains":true},{"actorID":"605","targetID":"620","newTargetID":"621","targetNumUses":"10"},{"actorID":"605","targetID":"617","newTargetID":"617","targetNumUses":"10","targetRemains":true},{"actorID":"605","targetID":"617","newTargetID":"618","targetNumUses":"10"}],"version":52,"complexity":57,"techTree":[{"decay":"3s"},{"id":"603","nodes":[{"decay":"3s"},{"id":"534","nodes":[{"id":"540","nodes":[]}]}]}]}