{"id":"616","name":"Sheep Eating Carrot Row","transitionsToward":[{"actorID":"575","targetID":"400","newTargetID":"616"}],"transitionsAway":[{"targetID":"616","newTargetID":"575","decay":"2s"},{"actorID":"616","newActorID":"615","newTargetID":"575"}],"version":52,"numUses":5,"complexity":143,"difficulty":0.601957585644372,"techTree":[{"id":"575","nodes":[{"decay":"3s"},{"id":"602","nodes":[{"id":"258","nodes":[]},{"id":"542","nodes":[]}]}]},{"id":"400","nodes":[{"decay":"2m"},{"id":"398","nodes":[{"decay":"2m"},{"id":"399","nodes":[]}]}]}]}