{"id":"672","name":"Cistern","transitionsToward":[{"actorID":"660","targetID":"670","newTargetUses":"last","newActorID":"659","newTargetID":"672","hand":true},{"actorID":"659","targetID":"671","newActorID":"660","newTargetID":"672","hand":true},{"actorID":"660","targetID":"673","newTargetUses":"last","newActorID":"659","newTargetID":"672","hand":true}],"transitionsAway":[{"actorID":"659","targetID":"672","newTargetUses":"-1","newActorID":"660","newTargetID":"672","targetRemains":true,"hand":true},{"actorID":"659","targetID":"672","targetUses":"last","newActorID":"660","newTargetID":"673","hand":true},{"actorID":"660","targetID":"672","newTargetUses":"+1","newActorID":"659","newTargetID":"672","targetRemains":true,"hand":true},{"actorID":"660","targetID":"672","targetUses":"max","newActorID":"659","newTargetID":"671","hand":true}],"transitionsTimed":[],"version":62,"numUses":9,"depth":66,"blocksWalking":true,"techTree":[{"id":"660","nodes":[{"id":"382","nodes":[{"id":"235","nodes":[]},{"id":"141","nodes":null}]},{"id":"1099","nodes":[{"id":"382","nodes":[]},{"id":"659","nodes":[]}]}]},{"id":"670","nodes":[{"id":"677","nodes":[{"id":"676","nodes":[]},{"id":"382","nodes":[]}]},{"id":"661","nodes":[{"id":"33","nodes":null},{"id":"33","nodes":null}]}]}],"recipe":{"steps":[[{"id":"675","actorID":"674","targetID":"235","hand":true}],[{"id":"678","actorID":"239","targetID":"675","hand":true}],[{"id":"679","actorID":"678","targetID":"304","hand":true}],[{"id":"382","count":3,"actorID":"235","targetID":"141","hand":true},{"id":"676","actorID":"679","hand":true}],[{"id":"677","actorID":"676","targetID":"382","hand":true},{"id":"661","actorID":"33","targetID":"33","hand":true}],[{"id":"660","subSteps":[[{"id":"1099","actorID":"382","targetID":"659","hand":true}],[{"id":"660","actorID":"382","targetID":"1099","hand":true}]]},{"id":"670","actorID":"677","targetID":"661","hand":true}],[{"id":"672","actorID":"660","targetID":"670","hand":true}]],"ingredients":["659","304","235","239","33","33","674","141"]}}