{"id":"749","name":"Yew Bow - just murdered","foodValue":"0","heatValue":"0","clothing":"n","numUses":"1","complexity":42,"techTree":[{"id":"152","nodes":[{"id":"148","nodes":[{"id":"134","nodes":[]},{"id":"149","nodes":[]}]},{"id":"151","nodes":[{"id":"59","nodes":[]},{"id":"131","nodes":[]}]}]}],"transitionsToward":[{"actorID":"152","newActorID":"749","newTargetID":"752","targetRemains":false,"hand":false,"tool":false}],"transitionsAway":[{"targetID":"749","newTargetID":"151","targetNumUses":"1","targetRemains":false,"hand":false,"tool":false,"decay":"30s"}]}