{"id":"813","name":"Stone Block with Chisel","transitionsToward":[{"actorID":"467","targetID":"811","newActorID":"467","newTargetID":"813","tool":true}],"transitionsAway":[{"targetID":"813","newActorID":"455","newTargetID":"812","hand":true}],"version":75,"complexity":388,"difficulty":0.8363338788870703,"techTree":[{"id":"467","nodes":[{"id":"462","nodes":[{"id":"454","nodes":[]},{"id":"67","nodes":[]}]},{"id":"345","nodes":[{"id":"339","nodes":[]}]}]},{"id":"811","nodes":[{"id":"455","nodes":[{"id":"451","nodes":[]}]},{"id":"504","nodes":[{"id":"506","nodes":[]}]}]}]}