{"id":"82","name":"Fire","transitionsToward":[{"actorID":"72","targetID":"80","newTargetID":"82","hand":true},{"targetID":"83","newTargetID":"82","decay":"30s"},{"actorID":"72","targetID":"85","newTargetID":"82","hand":true},{"actorID":"248","targetID":"72","newActorID":"248","newTargetID":"82","hand":true,"tool":true},{"targetID":"346","newTargetID":"82","decay":"4m"},{"actorID":"72","targetID":"1417","newTargetID":"82","hand":true}],"transitionsAway":[{"actorID":"220","targetID":"82","newTargetID":"82","targetRemains":true,"hand":true},{"actorID":"67","targetID":"82","newActorID":"248","newTargetID":"82","targetRemains":true,"hand":true},{"actorID":"72","targetID":"82","newTargetID":"83","hand":true},{"actorID":"516","targetID":"82","newActorID":"520","newTargetID":"82","targetRemains":true,"hand":true},{"actorID":"185","targetID":"82","newActorID":"187","newTargetID":"82","targetRemains":true,"hand":true},{"actorID":"1120","targetID":"82","newActorID":"1122","newTargetID":"82","targetRemains":true,"hand":true},{"actorID":"2103","targetID":"82","newActorID":"2105","newTargetID":"82","targetRemains":true,"hand":true},{"actorID":"344","targetID":"82","newTargetID":"346","hand":true},{"actorID":"345","targetID":"82","newTargetID":"346","hand":true},{"actorID":"560","targetID":"82","newActorID":"1368","newTargetID":"82","targetRemains":true,"hand":true}],"transitionsTimed":[{"targetID":"82","newTargetID":"85","decay":"1m"}],"version":20,"heatValue":4,"depth":10,"techTree":[{"id":"72","nodes":[{"id":"71","nodes":[{"id":"34","nodes":[]},{"id":"70","nodes":[]}]},{"id":"132","nodes":[{"id":"153","nodes":null}]}]},{"id":"80","nodes":[{"decay":"5s"},{"id":"78","nodes":[{"id":"77","nodes":[]},{"id":"61","nodes":[]}]}]}],"recipe":{"steps":[[{"id":"75","actorID":"74","targetID":"67","hand":true}],[{"id":"77","actorID":"62","targetID":"75","hand":true},{"id":"61","targetID":"49","hand":true}],[{"id":"78","actorID":"77","targetID":"61","hand":true}],[{"id":"72","subSteps":[[{"id":"132","targetID":"153","hand":true}],[{"id":"72","actorID":"71","targetID":"132","hand":true}]]},{"id":"80","targetID":"78","decay":"5s"}],[{"id":"82","actorID":"72","targetID":"80","hand":true}]],"ingredients":["74","71","67","62","49","153"]}}