{"id":"842","name":"Bell Tower -  ready to ring","transitionsToward":[{"targetID":"835","newTargetID":"842","decay":"3s"},{"targetID":"841","newTargetID":"842","decay":"20m"},{"targetID":"840","newTargetID":"842","decay":"20m"}],"transitionsAway":[{"targetID":"842","newTargetID":"839","hand":true,"tool":true}],"version":75,"complexity":730,"difficulty":0.9896449704142012,"techTree":[{"decay":"3s"},{"id":"835","nodes":[{"id":"836","nodes":[{"id":"767","nodes":[]},{"id":"809","nodes":[]}]},{"id":"834","nodes":[{"id":"556","nodes":[]},{"id":"833","nodes":[]}]}]}],"recipe":{"steps":[[{"id":"503","count":12,"actorID":"502","targetID":"32"}],[{"id":"508","count":12,"actorID":"455","targetID":"503"}],[{"id":"546","count":12,"actorID":"467","targetID":"508"}],[{"id":"506","count":12,"targetID":"546","hand":true}],[{"id":"504","count":12,"targetID":"506","hand":true}],[{"id":"811","count":12,"actorID":"455","targetID":"504"}],[{"id":"813","count":12,"actorID":"467","targetID":"811"}],[{"id":"812","count":12,"targetID":"813","hand":true},{"id":"108","actorID":"33","targetID":"107"}],[{"id":"814","actorID":"812","targetID":"108"}],[{"id":"815","actorID":"812","targetID":"814"}],[{"id":"816","targetID":"815","decay":"3h"}],[{"id":"819","actorID":"812","targetID":"816"}],[{"id":"818","actorID":"812","targetID":"819"}],[{"id":"820","targetID":"818","decay":"3h"}],[{"id":"822","actorID":"812","targetID":"820"}],[{"id":"823","actorID":"812","targetID":"822"}],[{"id":"824","targetID":"823","decay":"3h"}],[{"id":"825","actorID":"812","targetID":"824"}],[{"id":"681","count":2,"actorID":"684","targetID":"680"},{"id":"826","actorID":"812","targetID":"825"}],[{"id":"686","count":2,"actorID":"235","targetID":"681"},{"id":"827","targetID":"826","decay":"3h"}],[{"id":"690","count":2,"actorID":"239","targetID":"686"},{"id":"828","actorID":"812","targetID":"827"}],[{"id":"691","count":2,"actorID":"690","targetID":"304"},{"id":"829","actorID":"812","targetID":"828"}],[{"id":"57","count":8,"targetID":"50","hand":true},{"id":"687","count":2,"actorID":"691"},{"id":"830","targetID":"829","decay":"3h"}],[{"id":"58","count":4,"actorID":"57","targetID":"57"},{"id":"689","count":2,"targetID":"687","hand":true},{"id":"831","actorID":"812","targetID":"830"}],[{"id":"59","count":2,"actorID":"58","targetID":"58"},{"id":"810","actorID":"689","targetID":"689"},{"id":"557","actorID":"67","targetID":"67"},{"id":"832","actorID":"812","targetID":"831"}],[{"id":"767","actorID":"59","targetID":"59"},{"id":"809","actorID":"441","targetID":"810"},{"id":"556","actorID":"462","targetID":"557"},{"id":"833","targetID":"832","decay":"3h"}],[{"id":"836","actorID":"767","targetID":"809"},{"id":"834","actorID":"556","targetID":"833"}],[{"id":"835","actorID":"836","targetID":"834"}],[{"id":"842","targetID":"835","decay":"3s"}]],"ingredients":["467","684","502","462","455","441","304","235","239","107","67","32","50","50","50","33","50","50","50","50","680","50","680"]}}