{"id":"851","name":"Broken Stone Tool","transitionsToward":[{"actorID":"850","actorUses":"last","targetID":"848","newActorID":"851","newTargetID":"213"},{"actorID":"850","actorUses":"last","targetID":"901","newActorID":"851","newTargetID":"213"}],"transitionsAway":[{"targetID":"851","decay":"1h"},{"actorID":"851","targetID":"620","newTargetUses":"-1","newTargetID":"620","targetRemains":true},{"actorID":"851","targetID":"620","targetUses":"last","newTargetID":"621"},{"actorID":"851","targetID":"617","newTargetUses":"-1","newTargetID":"617","targetRemains":true},{"actorID":"851","targetID":"617","targetUses":"last","newTargetID":"618"}],"version":79,"complexity":97,"difficulty":0.5073746312684366,"techTree":[{"id":"850","nodes":[{"id":"34","nodes":[{"id":"33","nodes":null},{"id":"32","nodes":null}]},{"id":"92","nodes":[{"id":"59","nodes":[]},{"id":"67","nodes":[]}]}]},{"id":"848","nodes":[{"id":"400","nodes":[{"decay":"2m"},{"id":"398","nodes":[]}]}]}],"recipe":{"steps":[[{"id":"395","targetID":"36","hand":true}],[{"id":"57","count":4,"targetID":"50","hand":true},{"id":"382","actorID":"235","targetID":"141"},{"id":"396","actorID":"395","targetID":"213"}],[{"id":"58","count":2,"actorID":"57","targetID":"57"},{"id":"399","actorID":"382","targetID":"396"}],[{"id":"59","actorID":"58","targetID":"58"}],[{"id":"92","actorID":"59","targetID":"67"},{"id":"400","targetID":"398","decay":"2m"}],[{"id":"850","actorID":"34","targetID":"92"},{"id":"848","targetID":"400","hand":true}],[{"id":"851","actorID":"850","targetID":"848"}]],"ingredients":["235","213","67","34","36","50","50","50","50","141"]}}